quasimoto/__init__.py
quasimoto/__main__.py
quasimoto/app.py
quasimoto/dev_requirements.txt
quasimoto/entry.py
quasimoto/py.typed
quasimoto/requirements.txt
quasimoto/commands/__init__.py
quasimoto/commands/all.py
quasimoto/commands/gen.py
quasimoto/enums/__init__.py
quasimoto/riff/__init__.py
quasimoto/riff/chunk.py
quasimoto/sampler/__init__.py
quasimoto/wave/__init__.py
quasimoto/wave/mixins.py
quasimoto/wave/protocol.py
quasimoto/wave/reader.py
quasimoto/wave/writer.py
quasimoto-0.2.1.dist-info/LICENSE
quasimoto-0.2.1.dist-info/METADATA
quasimoto-0.2.1.dist-info/WHEEL
quasimoto-0.2.1.dist-info/entry_points.txt
quasimoto-0.2.1.dist-info/top_level.txt
quasimoto-0.2.1.dist-info/RECORD
