Metadata-Version: 2.1
Name: quasimoto
Version: 0.2.1
Summary: A lossless audio generator.
Home-page: https://github.com/vkottler/quasimoto
Author: Vaughn Kottler
Author-email: Vaughn Kottler <vaughnkottler@gmail.com>
Maintainer-email: Vaughn Kottler <vaughnkottler@gmail.com>
Classifier: Programming Language :: Python :: 3.11
Classifier: Programming Language :: Python :: 3.12
Classifier: Operating System :: Microsoft :: Windows
Classifier: Operating System :: MacOS
Classifier: Operating System :: POSIX :: Linux
Classifier: Operating System :: Unix
Classifier: Development Status :: 5 - Production/Stable
Classifier: License :: OSI Approved :: MIT License
Requires-Python: >=3.11
License-File: LICENSE
Requires-Dist: matplotlib
Requires-Dist: scipy
Requires-Dist: vcorelib
Requires-Dist: runtimepy
Provides-Extra: test
Requires-Dist: pylint ; extra == 'test'
Requires-Dist: flake8 ; extra == 'test'
Requires-Dist: black ; extra == 'test'
Requires-Dist: ruff ; extra == 'test'
Requires-Dist: mypy ; extra == 'test'
Requires-Dist: isort ; extra == 'test'
Requires-Dist: yamllint ; extra == 'test'
Requires-Dist: yambs ; extra == 'test'
Requires-Dist: vmklib ; extra == 'test'
Requires-Dist: sphinx ; extra == 'test'
Requires-Dist: sphinx-book-theme ; extra == 'test'
Requires-Dist: setuptools-wrapper ; extra == 'test'
Requires-Dist: types-setuptools ; extra == 'test'
